pygoodle/__init__.py
pygoodle/command.py
pygoodle/connectivity.py
pygoodle/console.py
pygoodle/csv.py
pygoodle/enum.py
pygoodle/error.py
pygoodle/filesystem.py
pygoodle/format.py
pygoodle/log.py
pygoodle/progress.py
pygoodle/random.py
pygoodle/reflection.py
pygoodle/ssh.py
pygoodle/util.py
pygoodle/yaml.py
pygoodle/app/__init__.py
pygoodle/app/app.py
pygoodle/app/argument.py
pygoodle/app/argument_group.py
pygoodle/app/bool_argument.py
pygoodle/app/count_argument.py
pygoodle/app/mutually_exclusive_argument_group.py
pygoodle/app/single_argument.py
pygoodle/app/subcommand.py
pygoodle/ftp/__init__.py
pygoodle/ftp/file_type.py
pygoodle/ftp/file_wrapper.py
pygoodle/ftp/ftp.py
pygoodle/ftp/sort_type.py
pygoodle/git/__init__.py
pygoodle/git/constants.py
pygoodle/git/decorators.py
pygoodle/git/log.py
pygoodle/git/offline.py
pygoodle/git/online.py
pygoodle/git/process_output.py
pygoodle/git/model/__init__.py
pygoodle/git/model/change.py
pygoodle/git/model/commit.py
pygoodle/git/model/diff.py
pygoodle/git/model/factory.py
pygoodle/git/model/protocol.py
pygoodle/git/model/ref.py
pygoodle/git/model/remote.py
pygoodle/git/model/repo.py
pygoodle/git/model/submodule.py
pygoodle/git/model/branch/__init__.py
pygoodle/git/model/branch/branch.py
pygoodle/git/model/branch/local_branch.py
pygoodle/git/model/branch/remote_branch.py
pygoodle/git/model/branch/tracking_branch.py
pygoodle/git/model/tag/__init__.py
pygoodle/git/model/tag/local_tag.py
pygoodle/git/model/tag/remote_tag.py
pygoodle/git/model/tag/tag.py
pygoodle/tasks/__init__.py
pygoodle/tasks/progress_task_pool.py
pygoodle/tasks/task_pool.py
pygoodle-0.1.1.dist-info/METADATA
pygoodle-0.1.1.dist-info/WHEEL
pygoodle-0.1.1.dist-info/top_level.txt
pygoodle-0.1.1.dist-info/RECORD
